kymograph_py/__init__.py
kymograph_py/kymograph_py.py
python_kymograph-0.1.0.dist-info/licenses/LICENSE
python_kymograph-0.1.0.dist-info/METADATA
python_kymograph-0.1.0.dist-info/WHEEL
python_kymograph-0.1.0.dist-info/top_level.txt
python_kymograph-0.1.0.dist-info/RECORD
